{
    "variable": [
        {
            "id": "baseUrl",
            "key": "baseUrl",
            "type": "string",
            "name": "string",
            "value": "http:\/\/localhost:8000"
        }
    ],
    "info": {
        "name": "Alumni Club API",
        "_postman_id": "23bce28d-365a-4c16-bb6d-1f88bb65da02",
        "description": "Simple yet powerful api for alumni club app",
        "schema": "https:\/\/schema.getpostman.com\/json\/collection\/v2.1.0\/collection.json"
    },
    "item": [
        {
            "name": "Auth",
            "description": "",
            "item": [
                {
                    "name": "Login",
                    "request": {
                        "url": {
                            "host": "{{baseUrl}}",
                            "path": "api\/login",
                            "query": [],
                            "raw": "{{baseUrl}}\/api\/login"
                        },
                        "method": "POST",
                        "header": [
                            {
                                "key": "Content-Type",
                                "value": "application\/json"
                            },
                            {
                                "key": "Accept",
                                "value": "application\/json"
                            }
                        ],
                        "body": {
                            "mode": "raw",
                            "raw": "{\"email\":\"john@doe.com\",\"password\":\"password\"}"
                        },
                        "description": "This endpoint is used for user logging in.",
                        "auth": {
                            "type": "noauth"
                        }
                    },
                    "response": []
                },
                {
                    "name": "User endpoint",
                    "request": {
                        "url": {
                            "host": "{{baseUrl}}",
                            "path": "api\/user",
                            "query": [],
                            "raw": "{{baseUrl}}\/api\/user"
                        },
                        "method": "GET",
                        "header": [
                            {
                                "key": "Content-Type",
                                "value": "application\/json"
                            },
                            {
                                "key": "Accept",
                                "value": "application\/json"
                            }
                        ],
                        "body": null,
                        "description": "This endpoint returns the authenticated user's data."
                    },
                    "response": [
                        {
                            "header": [
                                {
                                    "key": "cache-control",
                                    "value": "no-cache, private"
                                },
                                {
                                    "key": "content-type",
                                    "value": "application\/json"
                                },
                                {
                                    "key": "vary",
                                    "value": "Origin"
                                }
                            ],
                            "code": 401,
                            "body": "{\"message\":\"Unauthenticated.\"}",
                            "name": ""
                        }
                    ]
                },
                {
                    "name": "Register",
                    "request": {
                        "url": {
                            "host": "{{baseUrl}}",
                            "path": "api\/register",
                            "query": [],
                            "raw": "{{baseUrl}}\/api\/register"
                        },
                        "method": "POST",
                        "header": [
                            {
                                "key": "Content-Type",
                                "value": "application\/json"
                            },
                            {
                                "key": "Accept",
                                "value": "application\/json"
                            }
                        ],
                        "body": {
                            "mode": "raw",
                            "raw": "{\"name\":\"John Doe\",\"email\":\"john@doe.com\"}"
                        },
                        "description": "This endpoint is used for registering new user's into app."
                    },
                    "response": []
                },
                {
                    "name": "Change user details",
                    "request": {
                        "url": {
                            "host": "{{baseUrl}}",
                            "path": "api\/change-details",
                            "query": [],
                            "raw": "{{baseUrl}}\/api\/change-details"
                        },
                        "method": "PATCH",
                        "header": [
                            {
                                "key": "Content-Type",
                                "value": "application\/json"
                            },
                            {
                                "key": "Accept",
                                "value": "application\/json"
                            }
                        ],
                        "body": {
                            "mode": "raw",
                            "raw": "{\"date_of_birth\":\"10-04-1997\",\"gender\":\"male\",\"email_visible\":false,\"phone_number\":\"+3816060606\",\"phone_number_visible\":false,\"uni_start_year\":2020,\"uni_finish_year\":2023,\"bio\":\"\"}"
                        },
                        "description": "This endpoint is used for changing user details"
                    },
                    "response": []
                }
            ]
        },
        {
            "name": "Endpoints",
            "description": "",
            "item": [
                {
                    "name": "Change initial password",
                    "request": {
                        "url": {
                            "host": "{{baseUrl}}",
                            "path": "api\/change-initial-password",
                            "query": [],
                            "raw": "{{baseUrl}}\/api\/change-initial-password"
                        },
                        "method": "PUT",
                        "header": [
                            {
                                "key": "Content-Type",
                                "value": "application\/json"
                            },
                            {
                                "key": "Accept",
                                "value": "application\/json"
                            }
                        ],
                        "body": {
                            "mode": "raw",
                            "raw": "{\"password\":\"VZ>W{@g=\"}"
                        },
                        "description": "This endpoint is used only for changing user's initial password."
                    },
                    "response": []
                },
                {
                    "name": "Change password",
                    "request": {
                        "url": {
                            "host": "{{baseUrl}}",
                            "path": "api\/change-password",
                            "query": [],
                            "raw": "{{baseUrl}}\/api\/change-password"
                        },
                        "method": "PUT",
                        "header": [
                            {
                                "key": "Content-Type",
                                "value": "application\/json"
                            },
                            {
                                "key": "Accept",
                                "value": "application\/json"
                            }
                        ],
                        "body": {
                            "mode": "raw",
                            "raw": "{\"password\":\"password\",\"password_confirmation\":\"password\"}"
                        },
                        "description": "This endpoint is used for changing user passowrd."
                    },
                    "response": []
                }
            ]
        },
        {
            "name": "Jobs",
            "description": "",
            "item": [
                {
                    "name": "Create job endpoint",
                    "request": {
                        "url": {
                            "host": "{{baseUrl}}",
                            "path": "api\/jobs",
                            "query": [],
                            "raw": "{{baseUrl}}\/api\/jobs"
                        },
                        "method": "POST",
                        "header": [
                            {
                                "key": "Content-Type",
                                "value": "application\/json"
                            },
                            {
                                "key": "Accept",
                                "value": "application\/json"
                            }
                        ],
                        "body": {
                            "mode": "raw",
                            "raw": "{\"company_name\":\"Moto IT\",\"position\":\"Front-end Develper\",\"start_date\":\"10-04-1997\",\"end_date\":\"15-05-1997\",\"desc\":\"\"}"
                        },
                        "description": "This endpoint is used for creating job for authenticated user."
                    },
                    "response": []
                }
            ]
        }
    ],
    "auth": {
        "type": "noauth"
    }
}